fiboa_cli/__init__.py
fiboa_cli/create_stac.py
fiboa_cli/describe.py
fiboa_cli/registry.py
fiboa_cli/rename_extension.py
fiboa_cli/cli/__init__.py
fiboa_cli/cli/setup.py
fiboa_cli/conversion/__init__.py
fiboa_cli/conversion/convert_gml.py
fiboa_cli/conversion/converter_rest.py
fiboa_cli/conversion/fiboa_converter.py
fiboa_cli/datasets/__init__.py
fiboa_cli/datasets/ai4sf.py
fiboa_cli/datasets/at.py
fiboa_cli/datasets/at_crop.py
fiboa_cli/datasets/be_vlg.py
fiboa_cli/datasets/be_wal.py
fiboa_cli/datasets/br_ba_lem.py
fiboa_cli/datasets/br_conab.py
fiboa_cli/datasets/ch.py
fiboa_cli/datasets/cz.py
fiboa_cli/datasets/de_bb.py
fiboa_cli/datasets/de_mv.py
fiboa_cli/datasets/de_nds.py
fiboa_cli/datasets/de_nrw.py
fiboa_cli/datasets/de_sax.py
fiboa_cli/datasets/de_sh.py
fiboa_cli/datasets/de_sl.py
fiboa_cli/datasets/de_th.py
fiboa_cli/datasets/digifarm.py
fiboa_cli/datasets/dk.py
fiboa_cli/datasets/ec_be_vlg.py
fiboa_cli/datasets/ec_ee.py
fiboa_cli/datasets/ec_lt.py
fiboa_cli/datasets/ec_lv.py
fiboa_cli/datasets/ec_nl_crop.py
fiboa_cli/datasets/ec_ro.py
fiboa_cli/datasets/ec_si.py
fiboa_cli/datasets/es.py
fiboa_cli/datasets/es_an.py
fiboa_cli/datasets/es_ar.py
fiboa_cli/datasets/es_cat.py
fiboa_cli/datasets/es_cb.py
fiboa_cli/datasets/es_cl.py
fiboa_cli/datasets/es_cm.py
fiboa_cli/datasets/es_cn.py
fiboa_cli/datasets/es_ex.py
fiboa_cli/datasets/es_ga.py
fiboa_cli/datasets/es_ib.py
fiboa_cli/datasets/es_md.py
fiboa_cli/datasets/es_nc.py
fiboa_cli/datasets/es_pv.py
fiboa_cli/datasets/es_vc.py
fiboa_cli/datasets/fi.py
fiboa_cli/datasets/fr.py
fiboa_cli/datasets/hr.py
fiboa_cli/datasets/ie.py
fiboa_cli/datasets/india_10k.py
fiboa_cli/datasets/jecam.py
fiboa_cli/datasets/jp.py
fiboa_cli/datasets/lacuna_labels.py
fiboa_cli/datasets/lt.py
fiboa_cli/datasets/lu.py
fiboa_cli/datasets/lv.py
fiboa_cli/datasets/nl.py
fiboa_cli/datasets/nl_crop.py
fiboa_cli/datasets/nz.py
fiboa_cli/datasets/planet_afb.py
fiboa_cli/datasets/pt.py
fiboa_cli/datasets/se.py
fiboa_cli/datasets/si.py
fiboa_cli-0.20.3.dist-info/licenses/LICENSE
fiboa_cli-0.20.3.dist-info/METADATA
fiboa_cli-0.20.3.dist-info/WHEEL
fiboa_cli-0.20.3.dist-info/entry_points.txt
fiboa_cli-0.20.3.dist-info/top_level.txt
fiboa_cli-0.20.3.dist-info/RECORD
