Metadata-Version: 2.4
Name: fiboa-cli
Version: 0.20.3
Summary: CLI tools such as validation and file format conversion for fiboa.
Author: Matthias Mohr, Ivor Bosloper
License-Expression: Apache-2.0
Project-URL: Homepage, https://github.com/fiboa/cli
Project-URL: Bug Reports, https://github.com/fiboa/cli/issues
Project-URL: Source, https://github.com/fiboa/cli
Classifier: Development Status :: 4 - Beta
Classifier: Programming Language :: Python :: 3
Classifier: Programming Language :: Python :: 3.10
Classifier: Programming Language :: Python :: 3.11
Classifier: Programming Language :: Python :: 3.12
Classifier: Programming Language :: Python :: 3.13
Requires-Python: >=3.10
License-File: LICENSE
Requires-Dist: vecorel-cli==0.2.8
Dynamic: license-file
